adder/__init__.py
adder/tests/__init__.py
adder/tests/test_one_number.py
PyAdder-0.0.5.dist-info/LICENSE.txt
PyAdder-0.0.5.dist-info/METADATA
PyAdder-0.0.5.dist-info/WHEEL
PyAdder-0.0.5.dist-info/top_level.txt
PyAdder-0.0.5.dist-info/RECORD
